websitemailer/__init__.py
websitemailer/driver.py
websitemailer/mailer.py
websitemailer/main.py
websitemailer/screenshots.py
websitemailer-1.1.1.dist-info/AUTHORS.rst
websitemailer-1.1.1.dist-info/LICENSE.txt
websitemailer-1.1.1.dist-info/METADATA
websitemailer-1.1.1.dist-info/WHEEL
websitemailer-1.1.1.dist-info/top_level.txt
websitemailer-1.1.1.dist-info/RECORD
