Metadata-Version: 2.1
Name: websitemailer
Version: 1.1.1
Summary: Add a short description here!
Home-page: https://github.com/city-of-baltimore/website-mailer
Author: Brian Seel
Author-email: Brian.Seel@baltimorecity.gov
License: MIT
Project-URL: Source, https://github.com/city-of-baltimore/website-mailer
Project-URL: Changelog, https://github.com/city-of-baltimore/website-mailer/commit/main
Project-URL: Tracker, https://github.com/city-of-baltimore/website-mailer/issues
Project-URL: Twitter, https://twitter.com/cylussec
Platform: any
Classifier: Development Status :: 4 - Beta
Classifier: Programming Language :: Python
License-File: LICENSE.txt
License-File: AUTHORS.rst
Requires-Dist: loguru
Requires-Dist: requests
Requires-Dist: pefile
Requires-Dist: selenium
Requires-Dist: configargparse
Requires-Dist: pyyaml
Requires-Dist: importlib-metadata ; python_version < "3.8"
Provides-Extra: testing
Requires-Dist: setuptools ; extra == 'testing'
Requires-Dist: pytest ; extra == 'testing'
Requires-Dist: pytest-cov ; extra == 'testing'
